selene_api/__init__.py
selene_api/api.py
selene_api/cloud.py
selene_api/exceptions.py
selene_api/identity.py
selene_api/pairing.py
selene_api/settings.py
selene_api/version.py
selene_api-0.0.3.dist-info/METADATA
selene_api-0.0.3.dist-info/WHEEL
selene_api-0.0.3.dist-info/top_level.txt
selene_api-0.0.3.dist-info/RECORD
